stack_archiver/__init__.py
stack_archiver/__main__.py
stack_archiver/_version.py
stack_archiver/main.hy
stack_archiver-0.1.2.dist-info/METADATA
stack_archiver-0.1.2.dist-info/WHEEL
stack_archiver-0.1.2.dist-info/dependency_links.txt
stack_archiver-0.1.2.dist-info/top_level.txt
stack_archiver-0.1.2.dist-info/RECORD
