Metadata-Version: 2.1
Name: stack-archiver
Version: 0.1.2
Summary: Archive your activity on Stack Exchange sites
Home-page: UNKNOWN
Author: Kodi B. Arfer
License: UNKNOWN
Project-URL: Source Code, https://github.com/Kodiologist/Stack-Exchange-Activity-Archiver
Platform: UNKNOWN
Classifier: Programming Language :: Python :: 3
Classifier: License :: OSI Approved :: GNU General Public License v3 or later (GPLv3+)
Classifier: Operating System :: OS Independent
Requires-Python: >=3.8
Requires-Dist: stackapi
